chilkat2.so
chilkat2-11.3.0.dist-info/METADATA
chilkat2-11.3.0.dist-info/WHEEL
chilkat2-11.3.0.dist-info/license.pdf
chilkat2-11.3.0.dist-info/top_level.txt
chilkat2-11.3.0.dist-info/RECORD
