Metadata-Version: 2.1
Name: chilkat2
Version: 11.3.0
Summary: Chilkat2 Python Module
Author: Chilkat Software
Author-email: info@chilkatsoft.com
Classifier: Development Status :: 5 - Production/Stable
Classifier: Intended Audience :: Developers
Classifier: Programming Language :: Python :: 3
Classifier: Programming Language :: Python :: 3 :: Only
Classifier: Programming Language :: Python :: 3.6
Classifier: Programming Language :: Python :: 3.7
Classifier: Programming Language :: Python :: 3.8
Classifier: Programming Language :: Python :: 3.9
Classifier: Programming Language :: Python :: 3.10
Classifier: Programming Language :: Python :: 3.11
Classifier: Programming Language :: Python :: 3.12
Classifier: Programming Language :: Python :: Implementation :: CPython
Classifier: Topic :: Software Development
Classifier: License :: Other/Proprietary License
Classifier: Operating System :: Microsoft :: Windows
Classifier: Operating System :: MacOS
Classifier: Operating System :: POSIX :: Linux
Project-URL: Homepage, https://www.chilkatsoft.com
Project-URL: Documentation, https://www.chilkatsoft.com/refdoc/python.asp
Project-URL: Release notes, https://cknotes.com/category/release-notes/
Requires-Python: >=3.6
License-File: license.pdf
